{"test_route":{"@Route":"\/test\/route","parameters":[]},"__routes":{"\/test\/route":{"controller":"Controllers\\ApiController","method":"test_route","route_parameters":{"1":"test","2":"route"},"parameters":[]},"\/test\/route\/dude":{"controller":"Controllers\\ApiController","method":"test_route_dude","route_parameters":{"1":"test","2":"route","3":"dude"},"parameters":[]},"\/test\/something":{"controller":"Controllers\\ApiController","method":"test_something","route_parameters":{"1":"test","2":"something"},"parameters":[]}},"test_route_dude":{"@Route":"\/test\/route\/dude","parameters":[]},"test_something":{"@Route":"\/test\/something","parameters":[]},"__timestamp":1577390610}